elote/__init__.py
elote/arenas/__init__.py
elote/arenas/base.py
elote/arenas/lambda_arena.py
elote/competitors/__init__.py
elote/competitors/base.py
elote/competitors/dwz.py
elote/competitors/ecf.py
elote/competitors/elo.py
elote/competitors/ensemble.py
elote/competitors/glicko.py
elote-0.1.0.dist-info/LICENSE.md
elote-0.1.0.dist-info/METADATA
elote-0.1.0.dist-info/WHEEL
elote-0.1.0.dist-info/top_level.txt
elote-0.1.0.dist-info/RECORD
