Metadata-Version: 2.1
Name: elote
Version: 0.1.0
Summary: Python module for rating bouts (like with Elo Rating)
Home-page: https://github.com/helton-tech/elote
Author: Will McGinnis
Author-email: will@helton.io
License: MIT
Download-URL: https://github.com/helton-tech/elote/tarball/0.1.0
Keywords: elo scoring rating
Platform: UNKNOWN
Classifier: Development Status :: 3 - Alpha
Classifier: Intended Audience :: Developers
Classifier: Programming Language :: Python :: 3
